mlcommons_box/__init__.py
mlcommons_box/check.py
mlcommons_box/generate_docker_template.py
mlcommons_box/main.py
mlcommons_box/parse.py
mlcommons_box/common/__init__.py
mlcommons_box/common/mlbox_metadata.py
mlcommons_box/common/utils.py
mlcommons_box/common/objects/__init__.py
mlcommons_box/common/objects/base.py
mlcommons_box/common/objects/common.py
mlcommons_box/common/objects/platform_config.py
mlcommons_box/common/objects/runner_description.py
mlcommons_box/schemas/__init__.py
mlcommons_box/schemas/mlbox-docker.yaml
mlcommons_box/schemas/mlbox-invoke.yaml
mlcommons_box/schemas/mlbox-platform-container.yaml
mlcommons_box/schemas/mlbox-platform-metadata.yaml
mlcommons_box/schemas/mlbox-platform.yaml
mlcommons_box/schemas/mlbox-root.yaml
mlcommons_box/schemas/mlbox-runner.yaml
mlcommons_box/schemas/mlbox-task-input.yaml
mlcommons_box/schemas/mlbox-task-output.yaml
mlcommons_box/schemas/mlbox-task.yaml
mlcommons_box/tests/__init__.py
mlcommons_box/tests/test_mlcommons_box_cli.py
mlcommons_box-0.2.3.dist-info/METADATA
mlcommons_box-0.2.3.dist-info/WHEEL
mlcommons_box-0.2.3.dist-info/entry_points.txt
mlcommons_box-0.2.3.dist-info/top_level.txt
mlcommons_box-0.2.3.dist-info/RECORD
