Metadata-Version: 2.1
Name: mlcommons-box
Version: 0.2.3
Summary: UNKNOWN
Home-page: UNKNOWN
License: Apache 2.0
Platform: UNKNOWN
Requires-Python: >=3.6
Requires-Dist: black (==v19.10b0)
Requires-Dist: flake8 (<4.0,>=3.7.9)
Requires-Dist: pytest-cov (<3.0,>=2.5)
Requires-Dist: pytest-mock (<2.0,>=1.7.1)
Requires-Dist: pytest (<6.0,>=5.0)
Requires-Dist: wheel (==0.32.2)
Requires-Dist: click (==7.1.2)
Requires-Dist: halo (==0.0.30)
Requires-Dist: mlspeclib (==1.0.0)
Requires-Dist: coloredlogs (==14.0)
Requires-Dist: cookiecutter (==1.7.2)
Requires-Dist: docker (==4.3.1)
Requires-Dist: pyyaml (==5.3.1)
